pyframelessutils/__init__.py
pyframelessutils/token_utilities/__init__.py
pyframelessutils/token_utilities/_token_utils.py
pyframelessutils/token_utilities/exceptions.py
test/__init__.py
test/conftest.py
py_frameless_utils-0.1.3.dist-info/METADATA
py_frameless_utils-0.1.3.dist-info/WHEEL
py_frameless_utils-0.1.3.dist-info/top_level.txt
py_frameless_utils-0.1.3.dist-info/RECORD
