Metadata-Version: 2.1
Name: py-frameless-utils
Version: 0.1.3
Summary: Various utilities not depending on Flask/FastAPI or other framework
Author: KE
Author-email: 
Keywords: python,decorator,token
Classifier: Development Status :: 1 - Planning
Classifier: Intended Audience :: Developers
Classifier: Programming Language :: Python :: 3.11
Classifier: Operating System :: Unix
Classifier: Operating System :: MacOS
Requires-Dist: PyJWT ==2.8.0
